{
    "essays": [
        {
           "title": "1",
           "body": "11",
           "date_at": 123123,
           "id": 1
        },
        {
           "title": "2",
           "body": "22",
           "date_at": 23124124,
           "id": 2
        },
        {
           "title": "3",
           "body": "33",
           "date_at": 21233124124,
           "id": 3
        },{
           "title": "1",
           "body": "11",
           "date_at": 123123,
           "id": 1
       },
       {
           "title": "2",
           "body": "22",
           "date_at": 23124124,
           "id": 2
       },
       {
           "title": "3",
           "body": "33",
           "date_at": 21233124124,
           "id": 3
        }
    ]
}
